setup.py
datastore/__init__.py
datastore.memcached.egg-info/PKG-INFO
datastore.memcached.egg-info/SOURCES.txt
datastore.memcached.egg-info/dependency_links.txt
datastore.memcached.egg-info/namespace_packages.txt
datastore.memcached.egg-info/requires.txt
datastore.memcached.egg-info/top_level.txt
datastore/memcached/__init__.py
datastore/memcached/test.py