Metadata-Version: 1.0
Name: datastore.memcached
Version: 0.1.1
Summary: memached datastore implementation
Home-page: http://github.com/datastore/datastore.memcached
Author: Juan Batiz-Benet
Author-email: juan@benet.ai
License: MIT License
Keywords: datastore,memcached
Platform: UNKNOWN
Classifier: Topic :: Database
Classifier: Topic :: Database :: Front-Ends
